LICENSE
MANIFEST.in
README
setup.py
setup_helper.py
test.py
demos/demo.py
demos/demo_server.py
demos/demo_sftp.py
demos/demo_simple.py
demos/forward.py
demos/interactive.py
demos/rforward.py
demos/test_rsa.key
demos/user_rsa_key
demos/user_rsa_key.pub
docs/api-objects.txt
docs/bug-index.html
docs/class-tree.html
docs/crarr.png
docs/epydoc.css
docs/epydoc.js
docs/frames.html
docs/help.html
docs/identifier-index.html
docs/index.html
docs/module-tree.html
docs/redirect.html
docs/since-index.html
docs/ssh-module.html
docs/ssh-pysrc.html
docs/ssh.Agent-class.html
docs/ssh.AgentKey-class.html
docs/ssh.AuthenticationException-class.html
docs/ssh.AutoAddPolicy-class.html
docs/ssh.BadAuthenticationType-class.html
docs/ssh.BadHostKeyException-class.html
docs/ssh.BufferedFile-class.html
docs/ssh.Channel-class.html
docs/ssh.ChannelException-class.html
docs/ssh.DSSKey-class.html
docs/ssh.HostKeys-class.html
docs/ssh.Message-class.html
docs/ssh.MissingHostKeyPolicy-class.html
docs/ssh.PKey-class.html
docs/ssh.PasswordRequiredException-class.html
docs/ssh.RSAKey-class.html
docs/ssh.RejectPolicy-class.html
docs/ssh.SFTP-class.html
docs/ssh.SFTPAttributes-class.html
docs/ssh.SFTPClient-class.html
docs/ssh.SFTPError-class.html
docs/ssh.SFTPFile-class.html
docs/ssh.SFTPHandle-class.html
docs/ssh.SFTPServer-class.html
docs/ssh.SFTPServerInterface-class.html
docs/ssh.SSHClient-class.html
docs/ssh.SSHConfig-class.html
docs/ssh.SSHException-class.html
docs/ssh.SecurityOptions-class.html
docs/ssh.ServerInterface-class.html
docs/ssh.SubsystemHandler-class.html
docs/ssh.Transport-class.html
docs/ssh.WarningPolicy-class.html
docs/ssh.agent-module.html
docs/ssh.agent-pysrc.html
docs/ssh.auth_handler-module.html
docs/ssh.auth_handler-pysrc.html
docs/ssh.ber-module.html
docs/ssh.ber-pysrc.html
docs/ssh.ber.BER-class.html
docs/ssh.ber.BERException-class.html
docs/ssh.buffered_pipe-module.html
docs/ssh.buffered_pipe-pysrc.html
docs/ssh.buffered_pipe.BufferedPipe-class.html
ssh.egg-info/PKG-INFO
ssh.egg-info/SOURCES.txt
ssh.egg-info/dependency_links.txt
ssh.egg-info/requires.txt
ssh.egg-info/top_level.txt
