Metadata-Version: 1.0
Name: ssh
Version: 1.7.11
Summary: SSH2 protocol library
Home-page: UNKNOWN
Author: Jeff Forcier
Author-email: jeff@bitprophet.org
License: LGPL
Platform: Posix; MacOS X; Windows
Classifier: Development Status :: 5 - Production/Stable
Classifier: Intended Audience :: Developers
Classifier: License :: OSI Approved :: GNU Library or Lesser General Public License (LGPL)
Classifier: Operating System :: OS Independent
Classifier: Topic :: Internet
Classifier: Topic :: Security :: Cryptography
